openapi_client/__init__.py
openapi_client/api_client.py
openapi_client/api_response.py
openapi_client/configuration.py
openapi_client/exceptions.py
openapi_client/py.typed
openapi_client/rest.py
openapi_client/api/__init__.py
openapi_client/api/analysis_history_api.py
openapi_client/api/artist_api.py
openapi_client/api/audio_ai_api.py
openapi_client/api/image_ai_api.py
openapi_client/api/prompt_history_api.py
openapi_client/models/__init__.py
openapi_client/models/ai_influence.py
openapi_client/models/analysis_history_entry.py
openapi_client/models/analysis_history_entry_artist_profile_pictures.py
openapi_client/models/analysis_history_entry_attribution.py
openapi_client/models/analysis_history_entry_audio_attribution_analysis.py
openapi_client/models/analysis_history_entry_audio_attribution_analysis_master_inner.py
openapi_client/models/analysis_history_entry_audio_attribution_analysis_master_inner_values_inner.py
openapi_client/models/analysis_history_entry_audio_attribution_analysis_master_inner_values_inner_top_metrics.py
openapi_client/models/analysis_history_entry_audio_attribution_analysis_master_inner_values_inner_top_metrics_identical_matches.py
openapi_client/models/analysis_history_entry_audio_attribution_analysis_master_inner_values_inner_values_inner.py
openapi_client/models/analysis_history_entry_created_at.py
openapi_client/models/analysis_history_entry_error_message.py
openapi_client/models/analysis_history_entry_image_attribution_analysis.py
openapi_client/models/analysis_history_entry_image_attribution_analysis_similar_files_inner.py
openapi_client/models/analysis_history_entry_image_attribution_analysis_similar_files_inner_color_matching.py
openapi_client/models/analysis_history_entry_image_attribution_analysis_top_metrics.py
openapi_client/models/analysis_history_entry_image_attribution_analysis_top_metrics_attribution_likelihood.py
openapi_client/models/analysis_history_entry_image_attribution_analysis_top_metrics_color_matching.py
sureel_api_sdk-1.0.3.dist-info/LICENSE
sureel_api_sdk-1.0.3.dist-info/METADATA
sureel_api_sdk-1.0.3.dist-info/WHEEL
sureel_api_sdk-1.0.3.dist-info/top_level.txt
sureel_api_sdk-1.0.3.dist-info/RECORD
